tanh_sinh/__init__.py
tanh_sinh/_main.py
tanh_sinh-0.3.16.dist-info/METADATA
tanh_sinh-0.3.16.dist-info/WHEEL
tanh_sinh-0.3.16.dist-info/top_level.txt
tanh_sinh-0.3.16.dist-info/RECORD
